ForIocCrawler-1.2.1.data/scripts/fic
crawler/__init__.py
crawler/crawler.py
crawler/crawlerdata.py
crawler/crawlererr.py
crawler/exporter.py
crawler/data/config.ini
crawler/data/pattern.ini
crawler/data/whitelist.ini
ForIocCrawler-1.2.1.dist-info/LICENSE
ForIocCrawler-1.2.1.dist-info/METADATA
ForIocCrawler-1.2.1.dist-info/WHEEL
ForIocCrawler-1.2.1.dist-info/top_level.txt
ForIocCrawler-1.2.1.dist-info/RECORD
