Metadata-Version: 2.1
Name: ForIocCrawler
Version: 1.2.1
Summary: A forensic ioc extractor
Home-page: https://github.com/rs-develop/forioccrawler
Author: rs-develop
Author-email: rsdevelop.contact@gmail.com
Project-URL: Bug Tracker, https://github.com/rs-develop/ForIocCrawler/issues
Classifier: Programming Language :: Python :: 3
Classifier: License :: OSI Approved :: MIT License
Classifier: Operating System :: OS Independent
Requires-Python: >=3.8
License-File: LICENSE
